pyscan_annek/__init__.py
pyscan_annek/cli.py
pyscan_annek/pymail.py
pyscan_annek/shelf.py
pyscan_annek/sweep.py
pyscan_annek-0.2.0.dist-info/entry_points.txt
pyscan_annek-0.2.0.dist-info/LICENSE
pyscan_annek-0.2.0.dist-info/WHEEL
pyscan_annek-0.2.0.dist-info/METADATA
pyscan_annek-0.2.0.dist-info/RECORD
