Metadata-Version: 2.1
Name: pyscan-annek
Version: 0.2.0
Summary: Scan for hosts and identify
License: MIT
Author: Michael MacKenna
Author-email: mpmackenna@gmail.com
Requires-Python: >=3.7,<4.0
Classifier: License :: OSI Approved :: MIT License
Classifier: Programming Language :: Python :: 3
Classifier: Programming Language :: Python :: 3.7
Classifier: Programming Language :: Python :: 3.8
Requires-Dist: click (>=7.1.1,<8.0.0)
Requires-Dist: pywinrm (>=0.4.1,<0.5.0)
